django_country_kit/__init__.py
django_country_kit/base.py
django_country_kit/data.py
django_country_kit/fields.py
django_country_kit/models.py
django_country_kit/nationalities.py
django_country_kit/tests.py
django_country_kit/widgets.py
django_country_kit-0.0.7.dist-info/LICENSE
django_country_kit-0.0.7.dist-info/METADATA
django_country_kit-0.0.7.dist-info/WHEEL
django_country_kit-0.0.7.dist-info/top_level.txt
django_country_kit-0.0.7.dist-info/RECORD
